{
  "id": "2519ef26422a4e4982f3ea7d9a2b3894",
  "system_id": "c6d1029795b8d6aff79aa627693134d6b9289932",
  "start_time": "2025-10-24T14:32:28.016428+00:00",
  "end_time": "2025-10-24T17:59:58.629634+00:00",
  "targets": [],
  "force": false,
  "dvc_args": [
    "--keep-going"
  ],
  "status": "failed",
  "stages": {
    "_check-env-tex": {
      "start_time": "2025-10-24T14:32:29.910000",
      "end_time": "2025-10-24T14:32:35.321000",
      "status": "completed"
    },
    "analysis-AllFigCompare": {
      "start_time": "2025-10-24T14:32:35.321000",
      "end_time": "2025-10-24T14:33:33.589000",
      "status": "completed"
    },
    "postpro-AllFigCompare": {
      "start_time": "2025-10-24T14:33:33.589000",
      "end_time": "2025-10-24T14:34:37.979000",
      "status": "completed"
    },
    "analysis-AsymptoticBVectorFigFunc": {
      "start_time": "2025-10-24T14:34:37.979000",
      "end_time": "2025-10-24T14:35:42.016000",
      "status": "completed"
    },
    "postpro-AsymptoticBVectorFigFunc": {
      "start_time": "2025-10-24T14:35:42.016000",
      "end_time": "2025-10-24T14:36:53.492000",
      "status": "completed"
    },
    "analysis-Comparison": {
      "start_time": "2025-10-24T14:36:53.492000",
      "end_time": "2025-10-24T14:40:42.865000",
      "status": "completed"
    },
    "analysis-Constraints": {
      "start_time": "2025-10-24T14:40:42.865000",
      "end_time": "2025-10-24T14:41:49.774000",
      "status": "completed"
    },
    "postpro-Constraints": {
      "start_time": "2025-10-24T14:41:49.774000",
      "end_time": "2025-10-24T14:43:25.363000",
      "status": "completed"
    },
    "analysis-Cost": {
      "start_time": "2025-10-24T14:43:25.363000",
      "end_time": "2025-10-24T14:44:28.776000",
      "status": "completed"
    },
    "postpro-Cost": {
      "start_time": "2025-10-24T14:44:28.776000",
      "end_time": "2025-10-24T14:45:46.771000",
      "status": "completed"
    },
    "analysis-DampingPlateStructures": {
      "start_time": "2025-10-24T14:45:46.771000",
      "end_time": "2025-10-24T14:47:05.099000",
      "status": "completed"
    },
    "postpro-DampingPlateStructures": {
      "start_time": "2025-10-24T14:47:05.099000",
      "end_time": "2025-10-24T14:48:25.874000",
      "status": "completed"
    },
    "analysis-DescFcns": {
      "start_time": "2025-10-24T14:48:25.874000",
      "end_time": "2025-10-24T14:49:39.292000",
      "status": "completed"
    },
    "postpro-DescFcns": {
      "start_time": "2025-10-24T14:49:39.292000",
      "end_time": "2025-10-24T14:51:15.735000",
      "status": "completed"
    },
    "analysis-DesignSpaceExploration": {
      "start_time": "2025-10-24T14:51:15.735000",
      "end_time": "2025-10-24T14:53:44.602000",
      "status": "completed"
    },
    "postpro-DesignSpaceExploration": {
      "start_time": "2025-10-24T14:53:44.602000",
      "end_time": "2025-10-24T14:54:53.390000",
      "status": "completed"
    },
    "analysis-DesignVars": {
      "start_time": "2025-10-24T14:54:53.390000",
      "end_time": "2025-10-24T14:56:14.747000",
      "status": "completed"
    },
    "postpro-DesignVars": {
      "start_time": "2025-10-24T14:56:14.747000",
      "end_time": "2025-10-24T14:57:35.631000",
      "status": "completed"
    },
    "analysis-ForceSaturationFigFunc": {
      "start_time": "2025-10-24T14:57:35.631000",
      "end_time": "2025-10-24T14:58:46.500000",
      "status": "completed"
    },
    "postpro-ForceSaturationFigFunc": {
      "start_time": "2025-10-24T14:58:46.500000",
      "end_time": "2025-10-24T15:00:23.681000",
      "status": "completed"
    },
    "analysis-GradientOptimFigFunc": {
      "start_time": "2025-10-24T15:00:23.681000",
      "end_time": "2025-10-24T15:02:49.495000",
      "status": "completed"
    },
    "analysis-HydroCoeffFigFunc": {
      "start_time": "2025-10-24T15:02:49.495000",
      "end_time": "2025-10-24T15:03:58.399000",
      "status": "completed"
    },
    "postpro-HydroCoeffFigFunc": {
      "start_time": "2025-10-24T15:03:58.399000",
      "end_time": "2025-10-24T15:05:04.689000",
      "status": "completed"
    },
    "analysis-JpdMultiplyFigFunc": {
      "start_time": "2025-10-24T15:05:04.689000",
      "end_time": "2025-10-24T15:06:04.676000",
      "status": "completed"
    },
    "postpro-JpdMultiplyFigFunc": {
      "start_time": "2025-10-24T15:06:04.676000",
      "end_time": "2025-10-24T15:07:14.558000",
      "status": "completed"
    },
    "analysis-LocationSensitivity": {
      "start_time": "2025-10-24T15:07:14.558000",
      "end_time": "2025-10-24T15:53:47.159000",
      "status": "completed"
    },
    "analysis-Meem": {
      "start_time": "2025-10-24T15:53:47.159000",
      "end_time": "2025-10-24T15:55:06.365000",
      "status": "completed"
    },
    "postpro-Meem": {
      "start_time": "2025-10-24T15:55:06.365000",
      "end_time": "2025-10-24T15:56:20.663000",
      "status": "completed"
    },
    "analysis-Multistart": {
      "start_time": "2025-10-24T15:56:20.663000",
      "end_time": "2025-10-24T16:05:29.925000",
      "status": "completed"
    },
    "postpro-Multistart": {
      "start_time": "2025-10-24T16:05:29.925000",
      "end_time": "2025-10-24T16:07:30.533000",
      "status": "completed"
    },
    "analysis-ParamSensitivities": {
      "start_time": "2025-10-24T16:07:30.533000",
      "end_time": "2025-10-24T16:28:51.693000",
      "status": "completed"
    },
    "postpro-ParamSensitivities": {
      "start_time": "2025-10-24T16:28:51.693000",
      "end_time": "2025-10-24T16:30:42.975000",
      "status": "completed"
    },
    "analysis-Parameters": {
      "start_time": "2025-10-24T16:30:42.975000",
      "end_time": "2025-10-24T16:31:46.226000",
      "status": "completed"
    },
    "postpro-Parameters": {
      "start_time": "2025-10-24T16:31:46.226000",
      "end_time": "2025-10-24T16:32:54.115000",
      "status": "completed"
    },
    "analysis-ParetoFigFunc": {
      "start_time": "2025-10-24T16:32:54.115000",
      "end_time": "2025-10-24T16:44:12.320000",
      "status": "completed"
    },
    "postpro-ParetoFigFunc": {
      "start_time": "2025-10-24T16:44:12.320000",
      "end_time": "2025-10-24T16:46:01.589000",
      "status": "completed"
    },
    "analysis-ParetoSweep": {
      "start_time": "2025-10-24T16:46:01.589000",
      "end_time": "2025-10-24T16:47:05.446000",
      "status": "completed"
    },
    "postpro-ParetoSweep": {
      "start_time": "2025-10-24T16:47:05.446000",
      "end_time": "2025-10-24T16:48:12.017000",
      "status": "completed"
    },
    "analysis-ReadNonMatlabFigs": {
      "start_time": "2025-10-24T16:48:12.017000",
      "end_time": "2025-10-24T16:49:08.038000",
      "status": "completed"
    },
    "postpro-ReadNonMatlabFigs": {
      "start_time": "2025-10-24T16:49:08.038000",
      "end_time": "2025-10-24T16:50:50.791000",
      "status": "completed"
    },
    "analysis-RunSingleFigFunc": {
      "start_time": "2025-10-24T16:50:50.791000",
      "end_time": "2025-10-24T16:51:57.160000",
      "status": "completed"
    },
    "postpro-RunSingleFigFunc": {
      "start_time": "2025-10-24T16:51:57.160000",
      "end_time": "2025-10-24T16:53:04.798000",
      "status": "completed"
    },
    "analysis-Runtime": {
      "start_time": "2025-10-24T16:53:04.798000",
      "end_time": "2025-10-24T17:03:20.218000",
      "status": "completed"
    },
    "postpro-Runtime": {
      "start_time": "2025-10-24T17:03:20.218000",
      "end_time": "2025-10-24T17:04:32.324000",
      "status": "completed"
    },
    "analysis-Slamming": {
      "start_time": "2025-10-24T17:04:32.324000",
      "end_time": "2025-10-24T17:05:57.963000",
      "status": "completed"
    },
    "postpro-Slamming": {
      "start_time": "2025-10-24T17:05:57.963000",
      "end_time": "2025-10-24T17:07:13.412000",
      "status": "completed"
    },
    "analysis-SparHydro": {
      "start_time": "2025-10-24T17:07:13.412000",
      "end_time": "2025-10-24T17:08:56.991000",
      "status": "completed"
    },
    "postpro-SparHydro": {
      "start_time": "2025-10-24T17:08:56.991000",
      "end_time": "2025-10-24T17:10:04.759000",
      "status": "completed"
    },
    "analysis-Validation": {
      "start_time": "2025-10-24T17:10:04.759000",
      "end_time": "2025-10-24T17:11:45.810000",
      "status": "completed"
    },
    "postpro-Validation": {
      "start_time": "2025-10-24T17:11:45.810000",
      "end_time": "2025-10-24T17:13:03.268000",
      "status": "completed"
    },
    "analysis-Wecsim": {
      "start_time": "2025-10-24T17:13:03.268000",
      "end_time": "2025-10-24T17:58:38.459000",
      "status": "completed"
    },
    "postpro-Wecsim": {
      "start_time": "2025-10-24T17:58:38.459000"
    },
    "stages: analysis-Comparison, analysis-GradientOptimFigFunc, analysis-LocationSensitivity and postpro-RunSingleFigFunc": {
      "end_time": "2025-10-24T17:59:52.970000",
      "status": "failed"
    }
  },
  "git_rev": "62c58e687821117610f1f16554e0eb56868e328a",
  "git_branch": "figures-class-2",
  "git_changed_files_before": [
    "dvc.lock",
    "mdocean/analysis/DesignSpaceExploration.m",
    "mdocean/analysis/GenericAnalysis.m"
  ],
  "git_staged_files_before": [],
  "git_untracked_files_before": [
    ".calkit/systems/c6d1029795b8d6aff79aa627693134d6b9289932.json"
  ],
  "git_changed_files_after": [
    "dvc.lock"
  ],
  "git_staged_files_after": [],
  "git_untracked_files_after": [
    ".calkit/systems/c6d1029795b8d6aff79aa627693134d6b9289932.json"
  ],
  "dvc_status_before": {
    "_check-env-tex": [
      "always changed"
    ],
    "analysis-AllFigCompare": [
      {
        "changed deps": {
          "mdocean/analysis/GenericAnalysis.m": "modified"
        }
      }
    ],
    "postpro-AllFigCompare": [
      {
        "changed deps": {
          "mdocean/analysis/GenericAnalysis.m": "modified",
          "mdocean/plots/matlab_figs/make_slamming_plot.m": "modified",
          "mdocean/plots/matlab_figs/plot_drag_convergence.m": "modified",
          "results/AllFigCompare/intermed.mat": "modified"
        }
      },
      {
        "changed outs": {
          "results/AllFigCompare/runtime_bar_chart.pdf": "deleted",
          "results/AllFigCompare/end.mat": "deleted"
        }
      }
    ],
    "analysis-AsymptoticBVectorFigFunc": [
      {
        "changed deps": {
          "mdocean/analysis/GenericAnalysis.m": "modified"
        }
      }
    ],
    "postpro-AsymptoticBVectorFigFunc": [
      {
        "changed deps": {
          "mdocean/analysis/GenericAnalysis.m": "modified",
          "mdocean/plots/matlab_figs/make_slamming_plot.m": "modified",
          "mdocean/plots/matlab_figs/plot_drag_convergence.m": "modified",
          "results/AsymptoticBVectorFigFunc/intermed.mat": "modified"
        }
      },
      {
        "changed outs": {
          "results/AsymptoticBVectorFigFunc/asymptotic_b_vector.pdf": "deleted",
          "results/AsymptoticBVectorFigFunc/end.mat": "deleted"
        }
      }
    ],
    "analysis-Comparison": [
      {
        "changed deps": {
          "mdocean/analysis/Comparison.m": "modified",
          "mdocean/analysis/GenericAnalysis.m": "modified",
          "mdocean/optimization/gradient_optim.m": "modified",
          "mdocean/plots/matlab_figs/compare.m": "modified",
          "mdocean/plots/matlab_figs/make_slamming_plot.m": "modified",
          "mdocean/plots/matlab_figs/plot_drag_convergence.m": "modified",
          "mdocean/plots/matlab_figs/plot_power_matrix.m": "modified",
          "mdocean/plots/matlab_figs/visualize_geometry.m": "modified"
        }
      },
      {
        "changed outs": {
          "results/Comparison/intermed.mat": "deleted"
        }
      }
    ],
    "postpro-Comparison": [
      {
        "changed deps": {
          "mdocean/analysis/Comparison.m": "modified",
          "mdocean/analysis/GenericAnalysis.m": "modified",
          "mdocean/optimization/gradient_optim.m": "modified",
          "mdocean/plots/matlab_figs/compare.m": "modified",
          "mdocean/plots/matlab_figs/make_slamming_plot.m": "modified",
          "mdocean/plots/matlab_figs/plot_drag_convergence.m": "modified",
          "mdocean/plots/matlab_figs/plot_power_matrix.m": "modified",
          "mdocean/plots/matlab_figs/visualize_geometry.m": "modified",
          "results/Comparison/intermed.mat": "deleted"
        }
      }
    ],
    "analysis-Constraints": [
      {
        "changed deps": {
          "mdocean/analysis/GenericAnalysis.m": "modified"
        }
      }
    ],
    "postpro-Constraints": [
      {
        "changed deps": {
          "mdocean/analysis/GenericAnalysis.m": "modified"
        }
      }
    ],
    "analysis-Cost": [
      {
        "changed deps": {
          "mdocean/analysis/GenericAnalysis.m": "modified"
        }
      }
    ],
    "postpro-Cost": [
      {
        "changed deps": {
          "mdocean/analysis/GenericAnalysis.m": "modified"
        }
      }
    ],
    "analysis-DampingPlateStructures": [
      {
        "changed deps": {
          "mdocean/analysis/GenericAnalysis.m": "modified"
        }
      }
    ],
    "postpro-DampingPlateStructures": [
      {
        "changed deps": {
          "mdocean/analysis/DampingPlateStructures.m": "modified",
          "mdocean/analysis/GenericAnalysis.m": "modified",
          "mdocean/plots/matlab_figs/make_slamming_plot.m": "modified",
          "mdocean/plots/matlab_figs/plot_drag_convergence.m": "modified",
          "results/DampingPlateStructures/intermed.mat": "modified"
        }
      },
      {
        "changed outs": {
          "results/DampingPlateStructures/damping_plate_aspect_ratio.pdf": "deleted",
          "results/DampingPlateStructures/damping_plate_deflection.pdf": "deleted",
          "results/DampingPlateStructures/damping_plate_moment.pdf": "deleted",
          "results/DampingPlateStructures/end.mat": "deleted"
        }
      }
    ],
    "analysis-DescFcns": [
      {
        "changed deps": {
          "mdocean/analysis/GenericAnalysis.m": "modified"
        }
      }
    ],
    "postpro-DescFcns": [
      {
        "changed deps": {
          "mdocean/analysis/DescFcns.m": "modified",
          "mdocean/analysis/GenericAnalysis.m": "modified",
          "mdocean/plots/matlab_figs/make_slamming_plot.m": "modified",
          "mdocean/plots/matlab_figs/plot_drag_convergence.m": "modified",
          "mdocean/plots/matlab_figs/sin_desc_fcn_demo.m": "modified",
          "results/DescFcns/intermed.mat": "modified"
        }
      },
      {
        "changed outs": {
          "results/DescFcns/drag_desc_fcn.pdf": "deleted",
          "results/DescFcns/saturation_desc_fcn.pdf": "deleted",
          "results/DescFcns/end.mat": "deleted"
        }
      }
    ],
    "analysis-DesignSpaceExploration": [
      {
        "changed deps": {
          "mdocean/analysis/DesignSpaceExploration.m": "modified",
          "mdocean/analysis/GenericAnalysis.m": "modified"
        }
      }
    ],
    "postpro-DesignSpaceExploration": [
      {
        "changed deps": {
          "mdocean/analysis/DesignSpaceExploration.m": "modified",
          "mdocean/analysis/GenericAnalysis.m": "modified",
          "mdocean/plots/matlab_figs/make_slamming_plot.m": "modified",
          "mdocean/plots/matlab_figs/plot_drag_convergence.m": "modified",
          "mdocean/plots/matlab_figs/visualize_geometry.m": "modified",
          "results/DesignSpaceExploration/intermed.mat": "modified"
        }
      },
      {
        "changed outs": {
          "results/DesignSpaceExploration/experiments.pdf": "deleted",
          "results/DesignSpaceExploration/end.mat": "deleted"
        }
      }
    ],
    "analysis-DesignVars": [
      {
        "changed deps": {
          "mdocean/analysis/GenericAnalysis.m": "modified"
        }
      }
    ],
    "postpro-DesignVars": [
      {
        "changed deps": {
          "mdocean/analysis/GenericAnalysis.m": "modified"
        }
      }
    ],
    "analysis-ForceSaturationFigFunc": [
      {
        "changed deps": {
          "mdocean/analysis/GenericAnalysis.m": "modified"
        }
      }
    ],
    "postpro-ForceSaturationFigFunc": [
      {
        "changed deps": {
          "mdocean/analysis/GenericAnalysis.m": "modified",
          "mdocean/plots/matlab_figs/make_slamming_plot.m": "modified",
          "mdocean/plots/matlab_figs/plot_drag_convergence.m": "modified",
          "results/ForceSaturationFigFunc/intermed.mat": "modified"
        }
      },
      {
        "changed outs": {
          "results/ForceSaturationFigFunc/power_force_sensitivity.pdf": "deleted",
          "results/ForceSaturationFigFunc/runtime_sensitivity.pdf": "deleted",
          "results/ForceSaturationFigFunc/end.mat": "deleted"
        }
      }
    ],
    "analysis-GradientOptimFigFunc": [
      {
        "changed deps": {
          "mdocean/analysis/GenericAnalysis.m": "modified",
          "mdocean/analysis/GradientOptimFigFunc.m": "modified",
          "mdocean/inputs/parameters.m": "modified",
          "mdocean/optimization/gradient_optim.m": "modified",
          "mdocean/plots/matlab_figs/make_slamming_plot.m": "modified",
          "mdocean/plots/matlab_figs/plot_drag_convergence.m": "modified",
          "mdocean/plots/matlab_figs/plot_power_matrix.m": "modified",
          "mdocean/plots/matlab_figs/visualize_geometry.m": "modified"
        }
      },
      {
        "changed outs": {
          "results/GradientOptimFigFunc/intermed.mat": "deleted"
        }
      }
    ],
    "postpro-GradientOptimFigFunc": [
      {
        "changed deps": {
          "mdocean/analysis/GenericAnalysis.m": "modified",
          "mdocean/analysis/GradientOptimFigFunc.m": "modified",
          "mdocean/inputs/parameters.m": "modified",
          "mdocean/optimization/gradient_optim.m": "modified",
          "mdocean/plots/matlab_figs/make_slamming_plot.m": "modified",
          "mdocean/plots/matlab_figs/plot_drag_convergence.m": "modified",
          "mdocean/plots/matlab_figs/plot_power_matrix.m": "modified",
          "mdocean/plots/matlab_figs/visualize_geometry.m": "modified",
          "results/GradientOptimFigFunc/intermed.mat": "deleted"
        }
      }
    ],
    "analysis-HydroCoeffFigFunc": [
      {
        "changed deps": {
          "mdocean/analysis/GenericAnalysis.m": "modified"
        }
      }
    ],
    "postpro-HydroCoeffFigFunc": [
      {
        "changed deps": {
          "mdocean/analysis/GenericAnalysis.m": "modified",
          "mdocean/analysis/HydroCoeffFigFunc.m": "modified",
          "mdocean/inputs/parameters.m": "modified",
          "mdocean/plots/matlab_figs/make_slamming_plot.m": "modified",
          "mdocean/plots/matlab_figs/plot_drag_convergence.m": "modified",
          "mdocean/simulation/run/hydro_coeff_err.m": "modified",
          "results/HydroCoeffFigFunc/intermed.mat": "modified"
        }
      },
      {
        "changed outs": {
          "results/HydroCoeffFigFunc/hydro_coeff_err.pdf": "deleted",
          "results/HydroCoeffFigFunc/end.mat": "deleted"
        }
      }
    ],
    "analysis-JpdMultiplyFigFunc": [
      {
        "changed deps": {
          "mdocean/analysis/GenericAnalysis.m": "modified"
        }
      }
    ],
    "postpro-JpdMultiplyFigFunc": [
      {
        "changed deps": {
          "mdocean/analysis/GenericAnalysis.m": "modified",
          "mdocean/analysis/JpdMultiplyFigFunc.m": "modified",
          "mdocean/inputs/parameters.m": "modified",
          "mdocean/optimization/gradient_optim.m": "modified",
          "mdocean/plots/matlab_figs/make_slamming_plot.m": "modified",
          "mdocean/plots/matlab_figs/plot_drag_convergence.m": "modified",
          "mdocean/plots/matlab_figs/plot_power_matrix.m": "modified",
          "mdocean/plots/matlab_figs/visualize_geometry.m": "modified",
          "results/JpdMultiplyFigFunc/intermed.mat": "modified"
        }
      },
      {
        "changed outs": {
          "results/JpdMultiplyFigFunc/JPD_multiplication.pdf": "deleted",
          "results/JpdMultiplyFigFunc/end.mat": "deleted"
        }
      }
    ],
    "analysis-LocationSensitivity": [
      {
        "changed deps": {
          "mdocean/analysis/GenericAnalysis.m": "modified",
          "mdocean/analysis/LocationSensitivity.m": "modified",
          "mdocean/inputs/parameters.m": "modified",
          "mdocean/optimization/gradient_optim.m": "modified",
          "mdocean/optimization/sensitivities/location_sensitivity.m": "modified",
          "mdocean/plots/matlab_figs/make_slamming_plot.m": "modified",
          "mdocean/plots/matlab_figs/plot_drag_convergence.m": "modified",
          "mdocean/plots/matlab_figs/plot_power_matrix.m": "modified",
          "mdocean/plots/matlab_figs/visualize_geometry.m": "modified"
        }
      },
      {
        "changed outs": {
          "results/LocationSensitivity/intermed.mat": "deleted"
        }
      }
    ],
    "postpro-LocationSensitivity": [
      {
        "changed deps": {
          "mdocean/analysis/GenericAnalysis.m": "modified",
          "mdocean/analysis/LocationSensitivity.m": "modified",
          "mdocean/inputs/parameters.m": "modified",
          "mdocean/optimization/gradient_optim.m": "modified",
          "mdocean/optimization/sensitivities/location_sensitivity.m": "modified",
          "mdocean/plots/matlab_figs/make_slamming_plot.m": "modified",
          "mdocean/plots/matlab_figs/plot_drag_convergence.m": "modified",
          "mdocean/plots/matlab_figs/plot_power_matrix.m": "modified",
          "mdocean/plots/matlab_figs/visualize_geometry.m": "modified",
          "results/LocationSensitivity/intermed.mat": "deleted"
        }
      }
    ],
    "analysis-Meem": [
      {
        "changed deps": {
          "mdocean/analysis/GenericAnalysis.m": "modified"
        }
      }
    ],
    "postpro-Meem": [
      {
        "changed deps": {
          "mdocean/analysis/GenericAnalysis.m": "modified",
          "mdocean/inputs/parameters.m": "modified",
          "mdocean/plots/matlab_figs/make_slamming_plot.m": "modified",
          "mdocean/plots/matlab_figs/plot_drag_convergence.m": "modified",
          "results/Meem/intermed.mat": "modified"
        }
      },
      {
        "changed outs": {
          "results/Meem/meem_regions.pdf": "deleted",
          "results/Meem/meem_sparsity.pdf": "deleted",
          "results/Meem/meem_validation.pdf": "deleted",
          "results/Meem/meem_matching.pdf": "deleted",
          "results/Meem/meem_convergence.pdf": "deleted",
          "results/Meem/asymptotic_b_vector.pdf": "deleted",
          "results/Meem/end.mat": "deleted"
        }
      }
    ],
    "analysis-Multistart": [
      {
        "changed deps": {
          "mdocean/analysis/GenericAnalysis.m": "modified"
        }
      }
    ],
    "postpro-Multistart": [
      {
        "changed deps": {
          "mdocean/analysis/GenericAnalysis.m": "modified",
          "mdocean/inputs/parameters.m": "modified",
          "mdocean/optimization/gradient_optim.m": "modified",
          "mdocean/plots/matlab_figs/make_slamming_plot.m": "modified",
          "mdocean/plots/matlab_figs/plot_drag_convergence.m": "modified",
          "mdocean/plots/matlab_figs/plot_power_matrix.m": "modified",
          "mdocean/plots/matlab_figs/visualize_geometry.m": "modified",
          "results/Multistart/intermed.mat": "modified"
        }
      },
      {
        "changed outs": {
          "results/Multistart/multistart_convergence_tree.pdf": "deleted",
          "results/Multistart/multistart_parallel_coordinates.pdf": "deleted",
          "results/Multistart/multistart_results.tex": "deleted",
          "results/Multistart/end.mat": "deleted"
        }
      }
    ],
    "analysis-ParamSensitivities": [
      {
        "changed deps": {
          "mdocean/analysis/GenericAnalysis.m": "modified",
          "mdocean/inputs/parameters.m": "modified",
          "mdocean/optimization/gradient_optim.m": "modified",
          "mdocean/plots/matlab_figs/make_slamming_plot.m": "modified",
          "mdocean/plots/matlab_figs/plot_drag_convergence.m": "modified",
          "mdocean/plots/matlab_figs/plot_power_matrix.m": "modified",
          "mdocean/plots/matlab_figs/visualize_geometry.m": "modified"
        }
      },
      {
        "changed outs": {
          "results/ParamSensitivities/intermed.mat": "deleted"
        }
      }
    ],
    "postpro-ParamSensitivities": [
      {
        "changed deps": {
          "mdocean/analysis/GenericAnalysis.m": "modified",
          "mdocean/inputs/parameters.m": "modified",
          "mdocean/optimization/gradient_optim.m": "modified",
          "mdocean/plots/matlab_figs/make_slamming_plot.m": "modified",
          "mdocean/plots/matlab_figs/plot_drag_convergence.m": "modified",
          "mdocean/plots/matlab_figs/plot_power_matrix.m": "modified",
          "mdocean/plots/matlab_figs/visualize_geometry.m": "modified",
          "results/ParamSensitivities/intermed.mat": "deleted"
        }
      }
    ],
    "analysis-Parameters": [
      {
        "changed deps": {
          "mdocean/analysis/GenericAnalysis.m": "modified",
          "mdocean/inputs/parameters.m": "modified",
          "mdocean/plots/matlab_figs/make_slamming_plot.m": "modified",
          "mdocean/plots/matlab_figs/plot_drag_convergence.m": "modified"
        }
      }
    ],
    "postpro-Parameters": [
      {
        "changed deps": {
          "mdocean/analysis/GenericAnalysis.m": "modified",
          "mdocean/inputs/parameters.m": "modified",
          "mdocean/plots/matlab_figs/make_slamming_plot.m": "modified",
          "mdocean/plots/matlab_figs/plot_drag_convergence.m": "modified"
        }
      }
    ],
    "analysis-ParetoFigFunc": [
      {
        "changed deps": {
          "mdocean/analysis/GenericAnalysis.m": "modified",
          "mdocean/inputs/parameters.m": "modified",
          "mdocean/optimization/gradient_optim.m": "modified",
          "mdocean/plots/matlab_figs/make_slamming_plot.m": "modified",
          "mdocean/plots/matlab_figs/plot_drag_convergence.m": "modified",
          "mdocean/plots/matlab_figs/plot_power_matrix.m": "modified",
          "mdocean/plots/matlab_figs/visualize_geometry.m": "modified"
        }
      }
    ],
    "postpro-ParetoFigFunc": [
      {
        "changed deps": {
          "mdocean/analysis/GenericAnalysis.m": "modified",
          "mdocean/inputs/parameters.m": "modified",
          "mdocean/optimization/gradient_optim.m": "modified",
          "mdocean/plots/matlab_figs/make_slamming_plot.m": "modified",
          "mdocean/plots/matlab_figs/plot_drag_convergence.m": "modified",
          "mdocean/plots/matlab_figs/plot_power_matrix.m": "modified",
          "mdocean/plots/matlab_figs/visualize_geometry.m": "modified"
        }
      }
    ],
    "analysis-ParetoSweep": [
      {
        "changed deps": {
          "mdocean/analysis/GenericAnalysis.m": "modified",
          "mdocean/inputs/parameters.m": "modified",
          "mdocean/plots/matlab_figs/make_slamming_plot.m": "modified",
          "mdocean/plots/matlab_figs/plot_drag_convergence.m": "modified"
        }
      }
    ],
    "postpro-ParetoSweep": [
      {
        "changed deps": {
          "mdocean/analysis/GenericAnalysis.m": "modified",
          "mdocean/inputs/parameters.m": "modified",
          "mdocean/plots/matlab_figs/make_slamming_plot.m": "modified",
          "mdocean/plots/matlab_figs/plot_drag_convergence.m": "modified"
        }
      }
    ],
    "analysis-ReadNonMatlabFigs": [
      {
        "changed deps": {
          "mdocean/analysis/GenericAnalysis.m": "modified",
          "mdocean/inputs/parameters.m": "modified",
          "mdocean/plots/matlab_figs/make_slamming_plot.m": "modified",
          "mdocean/plots/matlab_figs/plot_drag_convergence.m": "modified"
        }
      }
    ],
    "postpro-ReadNonMatlabFigs": [
      {
        "changed deps": {
          "mdocean/analysis/GenericAnalysis.m": "modified",
          "mdocean/inputs/parameters.m": "modified",
          "mdocean/plots/matlab_figs/make_slamming_plot.m": "modified",
          "mdocean/plots/matlab_figs/plot_drag_convergence.m": "modified"
        }
      }
    ],
    "analysis-RunSingleFigFunc": [
      {
        "changed deps": {
          "mdocean/analysis/GenericAnalysis.m": "modified",
          "mdocean/analysis/RunSingleFigFunc.m": "modified",
          "mdocean/inputs/parameters.m": "modified",
          "mdocean/optimization/gradient_optim.m": "modified",
          "mdocean/plots/matlab_figs/make_slamming_plot.m": "modified",
          "mdocean/plots/matlab_figs/plot_drag_convergence.m": "modified",
          "mdocean/plots/matlab_figs/plot_power_matrix.m": "modified",
          "mdocean/plots/matlab_figs/visualize_geometry.m": "modified",
          "mdocean/simulation/run/run_single.m": "modified"
        }
      }
    ],
    "postpro-RunSingleFigFunc": [
      {
        "changed deps": {
          "mdocean/analysis/GenericAnalysis.m": "modified",
          "mdocean/analysis/RunSingleFigFunc.m": "modified",
          "mdocean/inputs/parameters.m": "modified",
          "mdocean/optimization/gradient_optim.m": "modified",
          "mdocean/plots/matlab_figs/make_slamming_plot.m": "modified",
          "mdocean/plots/matlab_figs/plot_drag_convergence.m": "modified",
          "mdocean/plots/matlab_figs/plot_power_matrix.m": "modified",
          "mdocean/plots/matlab_figs/visualize_geometry.m": "modified",
          "mdocean/simulation/run/run_single.m": "modified"
        }
      }
    ],
    "analysis-Runtime": [
      {
        "changed deps": {
          "mdocean/analysis/GenericAnalysis.m": "modified",
          "mdocean/inputs/parameters.m": "modified",
          "mdocean/plots/matlab_figs/make_slamming_plot.m": "modified",
          "mdocean/plots/matlab_figs/plot_drag_convergence.m": "modified"
        }
      }
    ],
    "postpro-Runtime": [
      {
        "changed deps": {
          "mdocean/analysis/GenericAnalysis.m": "modified",
          "mdocean/inputs/parameters.m": "modified",
          "mdocean/plots/matlab_figs/make_slamming_plot.m": "modified",
          "mdocean/plots/matlab_figs/plot_drag_convergence.m": "modified"
        }
      }
    ],
    "analysis-Slamming": [
      {
        "changed deps": {
          "mdocean/analysis/GenericAnalysis.m": "modified",
          "mdocean/inputs/parameters.m": "modified",
          "mdocean/plots/matlab_figs/make_slamming_plot.m": "modified",
          "mdocean/plots/matlab_figs/plot_drag_convergence.m": "modified"
        }
      }
    ],
    "postpro-Slamming": [
      {
        "changed deps": {
          "mdocean/analysis/GenericAnalysis.m": "modified",
          "mdocean/inputs/parameters.m": "modified",
          "mdocean/plots/matlab_figs/make_slamming_plot.m": "modified",
          "mdocean/plots/matlab_figs/plot_drag_convergence.m": "modified"
        }
      }
    ],
    "analysis-SparHydro": [
      {
        "changed deps": {
          "mdocean/analysis/GenericAnalysis.m": "modified",
          "mdocean/inputs/parameters.m": "modified",
          "mdocean/plots/matlab_figs/make_slamming_plot.m": "modified",
          "mdocean/plots/matlab_figs/plot_drag_convergence.m": "modified"
        }
      }
    ],
    "postpro-SparHydro": [
      {
        "changed deps": {
          "mdocean/analysis/GenericAnalysis.m": "modified",
          "mdocean/inputs/parameters.m": "modified",
          "mdocean/plots/matlab_figs/make_slamming_plot.m": "modified",
          "mdocean/plots/matlab_figs/plot_drag_convergence.m": "modified"
        }
      }
    ],
    "analysis-Validation": [
      {
        "changed deps": {
          "mdocean/analysis/GenericAnalysis.m": "modified",
          "mdocean/inputs/parameters.m": "modified",
          "mdocean/plots/matlab_figs/make_slamming_plot.m": "modified",
          "mdocean/plots/matlab_figs/plot_drag_convergence.m": "modified"
        }
      }
    ],
    "postpro-Validation": [
      {
        "changed deps": {
          "mdocean/analysis/GenericAnalysis.m": "modified",
          "mdocean/inputs/parameters.m": "modified",
          "mdocean/plots/matlab_figs/make_slamming_plot.m": "modified",
          "mdocean/plots/matlab_figs/plot_drag_convergence.m": "modified"
        }
      }
    ],
    "analysis-Wecsim": [
      {
        "changed deps": {
          "mdocean/analysis/GenericAnalysis.m": "modified",
          "mdocean/inputs/parameters.m": "modified",
          "mdocean/plots/matlab_figs/make_slamming_plot.m": "modified",
          "mdocean/plots/matlab_figs/plot_drag_convergence.m": "modified"
        }
      }
    ],
    "postpro-Wecsim": [
      {
        "changed deps": {
          "mdocean/analysis/GenericAnalysis.m": "modified",
          "mdocean/inputs/parameters.m": "modified",
          "mdocean/plots/matlab_figs/make_slamming_plot.m": "modified",
          "mdocean/plots/matlab_figs/plot_drag_convergence.m": "modified"
        }
      }
    ],
    "move-results": [
      {
        "changed deps": {
          "results": "modified"
        }
      }
    ],
    "build-RE-paper": [
      {
        "changed deps": {
          "pubs/renewable-energy-mdo/mdocean.tex": "modified",
          "pubs/renewable-energy-mdo/.latexmkrc": "modified",
          "pubs/renewable-energy-mdo/figs/manual": "modified",
          "pubs/renewable-energy-mdo/sections": "modified"
        }
      },
      {
        "changed outs": {
          "pubs/renewable-energy-mdo/out/mdocean.pdf": "modified",
          "pubs/renewable-energy-mdo/out/mdocean.synctex.gz": "modified",
          "pubs/renewable-energy-mdo/aux": "modified",
          "pubs/renewable-energy-mdo/mdocean.pdf": "deleted"
        }
      }
    ],
    "build-AOR-paper": [
      {
        "changed deps": {
          "pubs/applied-ocean-research-model/main.tex": "modified",
          "pubs/applied-ocean-research-model/.latexmkrc": "modified",
          "pubs/applied-ocean-research-model/sections": "modified",
          "pubs/applied-ocean-research-model/figs/from-matlab": "modified",
          "pubs/applied-ocean-research-model/figs/manual": "modified",
          "pubs/applied-ocean-research-model/tables": "modified",
          "mdocean/simulation/modules/OpenFLASH/pubs/src/meem-appendix.tex": "modified"
        }
      },
      {
        "changed outs": {
          "pubs/applied-ocean-research-model/out/main.pdf": "modified",
          "pubs/applied-ocean-research-model/out/main.synctex.gz": "modified",
          "pubs/applied-ocean-research-model/aux": "modified",
          "pubs/applied-ocean-research-model/main.pdf": "deleted"
        }
      }
    ]
  },
  "dvc_data_status_before": {
    "not_in_cache": [],
    "not_in_remote": [],
    "committed": {
      "modified": [
        "results/DesignVars/end.mat",
        "results/DesignVars/intermed.mat",
        "results/ForceSaturationFigFunc/intermed.mat",
        "results/Cost/end.mat",
        "results/Cost/intermed.mat",
        "results/DescFcns/intermed.mat",
        "results/AllFigCompare/intermed.mat",
        "results/AsymptoticBVectorFigFunc/intermed.mat",
        "results/DampingPlateStructures/intermed.mat",
        "results/HydroCoeffFigFunc/intermed.mat",
        "results/Constraints/end.mat",
        "results/Constraints/intermed.mat",
        "results/Multistart/intermed.mat",
        "results/Meem/intermed.mat",
        "results/JpdMultiplyFigFunc/intermed.mat",
        "results/DesignSpaceExploration/intermed.mat"
      ]
    },
    "uncommitted": {
      "deleted": [
        "pubs/applied-ocean-research-model/main.pdf",
        "pubs/renewable-energy-mdo/mdocean.pdf",
        "results/ForceSaturationFigFunc/power_force_sensitivity.pdf",
        "results/ForceSaturationFigFunc/end.mat",
        "results/ForceSaturationFigFunc/runtime_sensitivity.pdf",
        "results/DescFcns/drag_desc_fcn.pdf",
        "results/DescFcns/saturation_desc_fcn.pdf",
        "results/DescFcns/end.mat",
        "results/AllFigCompare/runtime_bar_chart.pdf",
        "results/AllFigCompare/end.mat",
        "results/Comparison/intermed.mat",
        "results/AsymptoticBVectorFigFunc/end.mat",
        "results/AsymptoticBVectorFigFunc/asymptotic_b_vector.pdf",
        "results/DampingPlateStructures/damping_plate_aspect_ratio.pdf",
        "results/DampingPlateStructures/damping_plate_moment.pdf",
        "results/DampingPlateStructures/end.mat",
        "results/DampingPlateStructures/damping_plate_deflection.pdf",
        "results/ParamSensitivities/intermed.mat",
        "results/HydroCoeffFigFunc/end.mat",
        "results/HydroCoeffFigFunc/hydro_coeff_err.pdf",
        "results/GradientOptimFigFunc/intermed.mat",
        "results/Multistart/end.mat",
        "results/Multistart/multistart_parallel_coordinates.pdf",
        "results/Multistart/multistart_results.tex",
        "results/Multistart/multistart_convergence_tree.pdf",
        "results/Meem/meem_matching.pdf",
        "results/Meem/meem_convergence.pdf",
        "results/Meem/meem_validation.pdf",
        "results/Meem/meem_regions.pdf",
        "results/Meem/asymptotic_b_vector.pdf",
        "results/Meem/meem_sparsity.pdf",
        "results/Meem/end.mat",
        "results/JpdMultiplyFigFunc/end.mat",
        "results/JpdMultiplyFigFunc/JPD_multiplication.pdf",
        "results/DesignSpaceExploration/end.mat",
        "results/DesignSpaceExploration/experiments.pdf",
        "results/LocationSensitivity/intermed.mat"
      ],
      "added": [
        "pubs/applied-ocean-research-model/out/main.pdf",
        "pubs/renewable-energy-mdo/out/mdocean.pdf"
      ]
    },
    "untracked": [],
    "unchanged": [
      "results/GradientOptimFigFunc/single_obj_convergence.pdf",
      "results/ReadNonMatlabFigs/trapezoid.pdf",
      "results/Runtime/intermed.mat",
      "results/ReadNonMatlabFigs/N2_diagram.pdf",
      "results/Validation/end.mat",
      "results/ReadNonMatlabFigs/sim_runtime.pdf",
      "results/Slamming/slamming_amplitude.pdf",
      "pubs/renewable-energy-mdo/figs/from-matlab/",
      "results/Parameters/end.mat",
      "results/RunSingleFigFunc/end.mat",
      "results/GradientOptimFigFunc/normalized_gradient.pdf",
      "results/Parameters/parameters.tex",
      "results/Slamming/end.mat",
      "results/ParamSensitivities/re_optim_objective_grid.pdf",
      "results/ParamSensitivities/re_optim_design_grid.pdf",
      "results/Cost/cost_parameters.tex",
      "results/DesignVars/design_vars.tex",
      "results/ParamSensitivities/re_optim_constraint_grid.pdf",
      "results/GradientOptimFigFunc/single_obj_opt_geometry.pdf",
      "results/ReadNonMatlabFigs/FBD.pdf",
      "results/ParetoFigFunc/pareto_front_with_design_images.pdf",
      "results/Validation/intermed.mat",
      "results/Wecsim/intermed.mat",
      "results/ParamSensitivities/nonlinear_objectives.pdf",
      "results/ReadNonMatlabFigs/damping_plate_flowchart.pdf",
      "results/Wecsim/end.mat",
      "results/GradientOptimFigFunc/dJ_dx_gradient.pdf",
      "results/RunSingleFigFunc/nominal_power_pdf.pdf",
      "results/GradientOptimFigFunc/single_obj_opt_power_matrix.pdf",
      "results/Comparison/end.mat",
      "results/ParetoSweep/sweep_num_seeds.pdf",
      "results/ParetoSweep/end.mat",
      "results/SparHydro/intermed.mat",
      "results/Parameters/intermed.mat",
      "results/Slamming/intermed.mat",
      "results/RunSingleFigFunc/nominal_power_matrix.pdf",
      "results/ParamSensitivities/post_optim_design_grid.pdf",
      "results/Runtime/sim_runtime.pdf",
      "results/ReadNonMatlabFigs/MEEM_geometry.pdf",
      "pubs/renewable-energy-mdo/tables/from-matlab/",
      "results/ParamSensitivities/post_optim_re_optim_objective_grid.pdf",
      "pubs/applied-ocean-research-model/figs/from-matlab/",
      "results/Runtime/hydro_runtime.pdf",
      "results/ParetoFigFunc/pareto_constraint_activity.pdf",
      "results/ReadNonMatlabFigs/intermed.mat",
      "results/ReadNonMatlabFigs/optimization_flowchart.pdf",
      "results/RunSingleFigFunc/slamming_model_comparison.pdf",
      "results/ParetoFigFunc/pareto_front_LCOE_contours.pdf",
      "results/Comparison/overlaid_geometry.pdf",
      "results/SparHydro/spar_added_mass.pdf",
      "results/ReadNonMatlabFigs/RM3_image.pdf",
      "results/ParamSensitivities/re_optim_design_tornado_J2.pdf",
      "results/GradientOptimFigFunc/lagrange_multipliers.pdf",
      "results/RunSingleFigFunc/nominal_geometry_viz.pdf",
      "pubs/renewable-energy-mdo/figs/manual/",
      "results/RunSingleFigFunc/drag_convergence.pdf",
      "results/ParamSensitivities/nonlinear_design_J1.pdf",
      "results/ParetoFigFunc/intermed.mat",
      "results/Runtime/end.mat",
      "pubs/applied-ocean-research-model/tables/from-matlab/",
      "results/ReadNonMatlabFigs/dimensions.pdf",
      "results/ParamSensitivities/post_optim_constraint_grid.pdf",
      "results/ParetoFigFunc/pareto_heuristics.pdf",
      "results/ParamSensitivities/end.mat",
      "results/Constraints/constraints.tex",
      "results/ReadNonMatlabFigs/graphical_abstract.pdf",
      "results/ParamSensitivities/re_optim_design_tornado_J1.pdf",
      "results/ReadNonMatlabFigs/equivalent_stiffness.pdf",
      "results/GradientOptimFigFunc/end.mat",
      "results/Comparison/probability_CDF.pdf",
      "results/LocationSensitivity/location_sensitivity.tex",
      "results/Runtime/dynamics_runtime.pdf",
      "results/ReadNonMatlabFigs/end.mat",
      "results/Wecsim/wecsim_all_sea_states.pdf",
      "results/ReadNonMatlabFigs/methodology_overview.pdf",
      "results/ParamSensitivities/re_optim_objective_tornado.pdf",
      "results/Wecsim/WECSim_errors.tex",
      "results/SparHydro/end.mat",
      "pubs/applied-ocean-research-model/figs/manual/",
      "results/Wecsim/WECSim_error_histograms_singlebody.pdf",
      "results/ParetoFigFunc/end.mat",
      "results/Comparison/optimal_design_vars.tex",
      "results/ParetoSweep/intermed.mat",
      "results/ReadNonMatlabFigs/WECSim_error_breakdown.pdf",
      "results/Validation/cost_vs_N_WEC.pdf",
      "results/Comparison/overlaid_hydro_coeffs.pdf",
      "results/Wecsim/WECSim_error_histograms_multibody.pdf",
      "results/Validation/validation.tex",
      "results/LocationSensitivity/end.mat",
      "results/Comparison/optimal_outputs.tex",
      "results/RunSingleFigFunc/intermed.mat",
      "results/ParamSensitivities/nonlinear_design_J2.pdf"
    ]
  },
  "dvc_status_after": {
    "_check-env-tex": [
      "always changed"
    ],
    "analysis-AllFigCompare": [
      {
        "changed deps": {
          "mdocean/analysis/GenericAnalysis.m": "modified"
        }
      }
    ],
    "postpro-AllFigCompare": [
      {
        "changed deps": {
          "mdocean/analysis/GenericAnalysis.m": "modified"
        }
      }
    ],
    "analysis-AsymptoticBVectorFigFunc": [
      {
        "changed deps": {
          "mdocean/analysis/GenericAnalysis.m": "modified"
        }
      }
    ],
    "postpro-AsymptoticBVectorFigFunc": [
      {
        "changed deps": {
          "mdocean/analysis/GenericAnalysis.m": "modified"
        }
      }
    ],
    "analysis-Comparison": [
      {
        "changed deps": {
          "mdocean/analysis/Comparison.m": "modified",
          "mdocean/analysis/GenericAnalysis.m": "modified",
          "mdocean/optimization/gradient_optim.m": "modified",
          "mdocean/optimization/sensitivities/delta_x.m": "modified",
          "mdocean/plots/matlab_figs/compare.m": "modified",
          "mdocean/plots/matlab_figs/make_slamming_plot.m": "modified",
          "mdocean/plots/matlab_figs/plot_drag_convergence.m": "modified",
          "mdocean/plots/matlab_figs/plot_power_matrix.m": "modified",
          "mdocean/plots/matlab_figs/visualize_geometry.m": "modified"
        }
      },
      {
        "changed outs": {
          "results/Comparison/intermed.mat": "deleted"
        }
      }
    ],
    "postpro-Comparison": [
      {
        "changed deps": {
          "mdocean/analysis/Comparison.m": "modified",
          "mdocean/analysis/GenericAnalysis.m": "modified",
          "mdocean/optimization/gradient_optim.m": "modified",
          "mdocean/optimization/sensitivities/delta_x.m": "modified",
          "mdocean/plots/matlab_figs/compare.m": "modified",
          "mdocean/plots/matlab_figs/make_slamming_plot.m": "modified",
          "mdocean/plots/matlab_figs/plot_drag_convergence.m": "modified",
          "mdocean/plots/matlab_figs/plot_power_matrix.m": "modified",
          "mdocean/plots/matlab_figs/visualize_geometry.m": "modified",
          "results/Comparison/intermed.mat": "deleted"
        }
      }
    ],
    "analysis-Constraints": [
      {
        "changed deps": {
          "mdocean/analysis/GenericAnalysis.m": "modified"
        }
      }
    ],
    "postpro-Constraints": [
      {
        "changed deps": {
          "mdocean/analysis/GenericAnalysis.m": "modified"
        }
      }
    ],
    "analysis-Cost": [
      {
        "changed deps": {
          "mdocean/analysis/GenericAnalysis.m": "modified"
        }
      }
    ],
    "postpro-Cost": [
      {
        "changed deps": {
          "mdocean/analysis/GenericAnalysis.m": "modified"
        }
      }
    ],
    "analysis-DampingPlateStructures": [
      {
        "changed deps": {
          "mdocean/analysis/GenericAnalysis.m": "modified"
        }
      }
    ],
    "postpro-DampingPlateStructures": [
      {
        "changed deps": {
          "mdocean/analysis/GenericAnalysis.m": "modified"
        }
      }
    ],
    "analysis-DescFcns": [
      {
        "changed deps": {
          "mdocean/analysis/GenericAnalysis.m": "modified"
        }
      }
    ],
    "postpro-DescFcns": [
      {
        "changed deps": {
          "mdocean/analysis/GenericAnalysis.m": "modified"
        }
      }
    ],
    "analysis-DesignSpaceExploration": [
      {
        "changed deps": {
          "mdocean/analysis/GenericAnalysis.m": "modified"
        }
      }
    ],
    "postpro-DesignSpaceExploration": [
      {
        "changed deps": {
          "mdocean/analysis/GenericAnalysis.m": "modified"
        }
      }
    ],
    "analysis-DesignVars": [
      {
        "changed deps": {
          "mdocean/analysis/GenericAnalysis.m": "modified"
        }
      }
    ],
    "postpro-DesignVars": [
      {
        "changed deps": {
          "mdocean/analysis/GenericAnalysis.m": "modified"
        }
      }
    ],
    "analysis-ForceSaturationFigFunc": [
      {
        "changed deps": {
          "mdocean/analysis/GenericAnalysis.m": "modified"
        }
      }
    ],
    "postpro-ForceSaturationFigFunc": [
      {
        "changed deps": {
          "mdocean/analysis/GenericAnalysis.m": "modified"
        }
      }
    ],
    "analysis-GradientOptimFigFunc": [
      {
        "changed deps": {
          "mdocean/analysis/GenericAnalysis.m": "modified",
          "mdocean/analysis/GradientOptimFigFunc.m": "modified",
          "mdocean/inputs/parameters.m": "modified",
          "mdocean/optimization/gradient_optim.m": "modified",
          "mdocean/optimization/sensitivities/delta_x.m": "modified",
          "mdocean/plots/matlab_figs/make_slamming_plot.m": "modified",
          "mdocean/plots/matlab_figs/plot_drag_convergence.m": "modified",
          "mdocean/plots/matlab_figs/plot_power_matrix.m": "modified",
          "mdocean/plots/matlab_figs/visualize_geometry.m": "modified"
        }
      },
      {
        "changed outs": {
          "results/GradientOptimFigFunc/intermed.mat": "deleted"
        }
      }
    ],
    "postpro-GradientOptimFigFunc": [
      {
        "changed deps": {
          "mdocean/analysis/GenericAnalysis.m": "modified",
          "mdocean/analysis/GradientOptimFigFunc.m": "modified",
          "mdocean/inputs/parameters.m": "modified",
          "mdocean/optimization/gradient_optim.m": "modified",
          "mdocean/optimization/sensitivities/delta_x.m": "modified",
          "mdocean/plots/matlab_figs/make_slamming_plot.m": "modified",
          "mdocean/plots/matlab_figs/plot_drag_convergence.m": "modified",
          "mdocean/plots/matlab_figs/plot_power_matrix.m": "modified",
          "mdocean/plots/matlab_figs/visualize_geometry.m": "modified",
          "results/GradientOptimFigFunc/intermed.mat": "deleted"
        }
      }
    ],
    "analysis-HydroCoeffFigFunc": [
      {
        "changed deps": {
          "mdocean/analysis/GenericAnalysis.m": "modified"
        }
      }
    ],
    "postpro-HydroCoeffFigFunc": [
      {
        "changed deps": {
          "mdocean/analysis/GenericAnalysis.m": "modified"
        }
      }
    ],
    "analysis-JpdMultiplyFigFunc": [
      {
        "changed deps": {
          "mdocean/analysis/GenericAnalysis.m": "modified",
          "mdocean/optimization/sensitivities/delta_x.m": "modified"
        }
      }
    ],
    "postpro-JpdMultiplyFigFunc": [
      {
        "changed deps": {
          "mdocean/analysis/GenericAnalysis.m": "modified",
          "mdocean/optimization/sensitivities/delta_x.m": "modified"
        }
      }
    ],
    "analysis-LocationSensitivity": [
      {
        "changed deps": {
          "mdocean/analysis/GenericAnalysis.m": "modified",
          "mdocean/analysis/LocationSensitivity.m": "modified",
          "mdocean/inputs/parameters.m": "modified",
          "mdocean/optimization/gradient_optim.m": "modified",
          "mdocean/optimization/sensitivities/delta_x.m": "modified",
          "mdocean/optimization/sensitivities/location_sensitivity.m": "modified",
          "mdocean/plots/matlab_figs/make_slamming_plot.m": "modified",
          "mdocean/plots/matlab_figs/plot_drag_convergence.m": "modified",
          "mdocean/plots/matlab_figs/plot_power_matrix.m": "modified",
          "mdocean/plots/matlab_figs/visualize_geometry.m": "modified"
        }
      },
      {
        "changed outs": {
          "results/LocationSensitivity/intermed.mat": "deleted"
        }
      }
    ],
    "postpro-LocationSensitivity": [
      {
        "changed deps": {
          "mdocean/analysis/GenericAnalysis.m": "modified",
          "mdocean/analysis/LocationSensitivity.m": "modified",
          "mdocean/inputs/parameters.m": "modified",
          "mdocean/optimization/gradient_optim.m": "modified",
          "mdocean/optimization/sensitivities/delta_x.m": "modified",
          "mdocean/optimization/sensitivities/location_sensitivity.m": "modified",
          "mdocean/plots/matlab_figs/make_slamming_plot.m": "modified",
          "mdocean/plots/matlab_figs/plot_drag_convergence.m": "modified",
          "mdocean/plots/matlab_figs/plot_power_matrix.m": "modified",
          "mdocean/plots/matlab_figs/visualize_geometry.m": "modified",
          "results/LocationSensitivity/intermed.mat": "deleted"
        }
      }
    ],
    "analysis-Meem": [
      {
        "changed deps": {
          "mdocean/analysis/GenericAnalysis.m": "modified"
        }
      }
    ],
    "postpro-Meem": [
      {
        "changed deps": {
          "mdocean/analysis/GenericAnalysis.m": "modified"
        }
      }
    ],
    "analysis-Multistart": [
      {
        "changed deps": {
          "mdocean/analysis/GenericAnalysis.m": "modified",
          "mdocean/optimization/sensitivities/delta_x.m": "modified"
        }
      }
    ],
    "postpro-Multistart": [
      {
        "changed deps": {
          "mdocean/analysis/GenericAnalysis.m": "modified",
          "mdocean/optimization/sensitivities/delta_x.m": "modified"
        }
      }
    ],
    "analysis-ParamSensitivities": [
      {
        "changed deps": {
          "mdocean/analysis/GenericAnalysis.m": "modified",
          "mdocean/optimization/sensitivities/delta_x.m": "modified"
        }
      }
    ],
    "postpro-ParamSensitivities": [
      {
        "changed deps": {
          "mdocean/analysis/GenericAnalysis.m": "modified",
          "mdocean/optimization/sensitivities/delta_x.m": "modified"
        }
      }
    ],
    "analysis-Parameters": [
      {
        "changed deps": {
          "mdocean/analysis/GenericAnalysis.m": "modified"
        }
      }
    ],
    "postpro-Parameters": [
      {
        "changed deps": {
          "mdocean/analysis/GenericAnalysis.m": "modified"
        }
      }
    ],
    "analysis-ParetoFigFunc": [
      {
        "changed deps": {
          "mdocean/analysis/GenericAnalysis.m": "modified",
          "mdocean/optimization/sensitivities/delta_x.m": "modified"
        }
      }
    ],
    "postpro-ParetoFigFunc": [
      {
        "changed deps": {
          "mdocean/analysis/GenericAnalysis.m": "modified",
          "mdocean/optimization/sensitivities/delta_x.m": "modified"
        }
      }
    ],
    "analysis-ParetoSweep": [
      {
        "changed deps": {
          "mdocean/analysis/GenericAnalysis.m": "modified"
        }
      }
    ],
    "postpro-ParetoSweep": [
      {
        "changed deps": {
          "mdocean/analysis/GenericAnalysis.m": "modified"
        }
      }
    ],
    "analysis-ReadNonMatlabFigs": [
      {
        "changed deps": {
          "mdocean/analysis/GenericAnalysis.m": "modified"
        }
      }
    ],
    "postpro-ReadNonMatlabFigs": [
      {
        "changed deps": {
          "mdocean/analysis/GenericAnalysis.m": "modified"
        }
      }
    ],
    "analysis-RunSingleFigFunc": [
      {
        "changed deps": {
          "mdocean/analysis/GenericAnalysis.m": "modified",
          "mdocean/optimization/sensitivities/delta_x.m": "modified"
        }
      }
    ],
    "postpro-RunSingleFigFunc": [
      {
        "changed deps": {
          "mdocean/analysis/GenericAnalysis.m": "modified",
          "mdocean/analysis/RunSingleFigFunc.m": "modified",
          "mdocean/inputs/parameters.m": "modified",
          "mdocean/optimization/gradient_optim.m": "modified",
          "mdocean/optimization/sensitivities/delta_x.m": "modified",
          "mdocean/plots/matlab_figs/make_slamming_plot.m": "modified",
          "mdocean/plots/matlab_figs/plot_drag_convergence.m": "modified",
          "mdocean/plots/matlab_figs/plot_power_matrix.m": "modified",
          "mdocean/plots/matlab_figs/visualize_geometry.m": "modified",
          "mdocean/simulation/run/run_single.m": "modified",
          "results/RunSingleFigFunc/intermed.mat": "modified"
        }
      },
      {
        "changed outs": {
          "results/RunSingleFigFunc/nominal_geometry_viz.pdf": "modified",
          "results/RunSingleFigFunc/nominal_power_pdf.pdf": "modified",
          "results/RunSingleFigFunc/nominal_power_matrix.pdf": "modified",
          "results/RunSingleFigFunc/drag_convergence.pdf": "deleted",
          "results/RunSingleFigFunc/slamming_model_comparison.pdf": "deleted",
          "results/RunSingleFigFunc/end.mat": "deleted"
        }
      }
    ],
    "analysis-Runtime": [
      {
        "changed deps": {
          "mdocean/analysis/GenericAnalysis.m": "modified"
        }
      }
    ],
    "postpro-Runtime": [
      {
        "changed deps": {
          "mdocean/analysis/GenericAnalysis.m": "modified"
        }
      }
    ],
    "analysis-Slamming": [
      {
        "changed deps": {
          "mdocean/analysis/GenericAnalysis.m": "modified"
        }
      }
    ],
    "postpro-Slamming": [
      {
        "changed deps": {
          "mdocean/analysis/GenericAnalysis.m": "modified"
        }
      }
    ],
    "analysis-SparHydro": [
      {
        "changed deps": {
          "mdocean/analysis/GenericAnalysis.m": "modified"
        }
      }
    ],
    "postpro-SparHydro": [
      {
        "changed deps": {
          "mdocean/analysis/GenericAnalysis.m": "modified"
        }
      }
    ],
    "analysis-Validation": [
      {
        "changed deps": {
          "mdocean/analysis/GenericAnalysis.m": "modified"
        }
      }
    ],
    "postpro-Validation": [
      {
        "changed deps": {
          "mdocean/analysis/GenericAnalysis.m": "modified"
        }
      }
    ],
    "analysis-Wecsim": [
      {
        "changed deps": {
          "mdocean/analysis/GenericAnalysis.m": "modified"
        }
      }
    ],
    "move-results": [
      {
        "changed deps": {
          "results": "modified"
        }
      }
    ],
    "build-RE-paper": [
      {
        "changed deps": {
          "pubs/renewable-energy-mdo/mdocean.tex": "modified",
          "pubs/renewable-energy-mdo/.latexmkrc": "modified",
          "pubs/renewable-energy-mdo/figs/manual": "modified",
          "pubs/renewable-energy-mdo/sections": "modified"
        }
      },
      {
        "changed outs": {
          "pubs/renewable-energy-mdo/out/mdocean.pdf": "modified",
          "pubs/renewable-energy-mdo/out/mdocean.synctex.gz": "modified",
          "pubs/renewable-energy-mdo/aux": "modified",
          "pubs/renewable-energy-mdo/mdocean.pdf": "deleted"
        }
      }
    ],
    "build-AOR-paper": [
      {
        "changed deps": {
          "pubs/applied-ocean-research-model/main.tex": "modified",
          "pubs/applied-ocean-research-model/.latexmkrc": "modified",
          "pubs/applied-ocean-research-model/sections": "modified",
          "pubs/applied-ocean-research-model/figs/from-matlab": "modified",
          "pubs/applied-ocean-research-model/figs/manual": "modified",
          "pubs/applied-ocean-research-model/tables": "modified",
          "mdocean/simulation/modules/OpenFLASH/pubs/src/meem-appendix.tex": "modified"
        }
      },
      {
        "changed outs": {
          "pubs/applied-ocean-research-model/out/main.pdf": "modified",
          "pubs/applied-ocean-research-model/out/main.synctex.gz": "modified",
          "pubs/applied-ocean-research-model/aux": "modified",
          "pubs/applied-ocean-research-model/main.pdf": "deleted"
        }
      }
    ]
  },
  "dvc_data_status_after": {
    "not_in_cache": [],
    "not_in_remote": [],
    "committed": {
      "modified": [
        "results/Runtime/dynamics_runtime.pdf",
        "results/Runtime/hydro_runtime.pdf",
        "results/Runtime/sim_runtime.pdf",
        "results/Runtime/end.mat",
        "results/Runtime/intermed.mat",
        "results/DesignVars/end.mat",
        "results/DesignVars/intermed.mat",
        "results/ForceSaturationFigFunc/power_force_sensitivity.pdf",
        "results/ForceSaturationFigFunc/intermed.mat",
        "results/ForceSaturationFigFunc/end.mat",
        "results/ForceSaturationFigFunc/runtime_sensitivity.pdf",
        "results/Cost/end.mat",
        "results/Cost/intermed.mat",
        "results/DescFcns/drag_desc_fcn.pdf",
        "results/DescFcns/intermed.mat",
        "results/DescFcns/saturation_desc_fcn.pdf",
        "results/DescFcns/end.mat",
        "results/ReadNonMatlabFigs/intermed.mat",
        "results/ReadNonMatlabFigs/N2_diagram.pdf",
        "results/ReadNonMatlabFigs/MEEM_geometry.pdf",
        "results/ReadNonMatlabFigs/FBD.pdf",
        "results/ReadNonMatlabFigs/end.mat",
        "results/ReadNonMatlabFigs/equivalent_stiffness.pdf",
        "results/ReadNonMatlabFigs/RM3_image.pdf",
        "results/ReadNonMatlabFigs/methodology_overview.pdf",
        "results/ReadNonMatlabFigs/sim_runtime.pdf",
        "results/ReadNonMatlabFigs/optimization_flowchart.pdf",
        "results/ReadNonMatlabFigs/damping_plate_flowchart.pdf",
        "results/ReadNonMatlabFigs/dimensions.pdf",
        "results/ReadNonMatlabFigs/trapezoid.pdf",
        "results/ReadNonMatlabFigs/WECSim_error_breakdown.pdf",
        "results/ReadNonMatlabFigs/graphical_abstract.pdf",
        "results/AllFigCompare/intermed.mat",
        "results/AllFigCompare/runtime_bar_chart.pdf",
        "results/AllFigCompare/end.mat",
        "results/Slamming/intermed.mat",
        "results/Slamming/slamming_amplitude.pdf",
        "results/Slamming/end.mat",
        "results/AsymptoticBVectorFigFunc/intermed.mat",
        "results/AsymptoticBVectorFigFunc/end.mat",
        "results/AsymptoticBVectorFigFunc/asymptotic_b_vector.pdf",
        "results/DampingPlateStructures/intermed.mat",
        "results/DampingPlateStructures/damping_plate_aspect_ratio.pdf",
        "results/DampingPlateStructures/damping_plate_moment.pdf",
        "results/DampingPlateStructures/end.mat",
        "results/DampingPlateStructures/damping_plate_deflection.pdf",
        "results/Validation/cost_vs_N_WEC.pdf",
        "results/Validation/end.mat",
        "results/Validation/intermed.mat",
        "results/ParamSensitivities/post_optim_constraint_grid.pdf",
        "results/ParamSensitivities/re_optim_design_grid.pdf",
        "results/ParamSensitivities/nonlinear_design_J2.pdf",
        "results/ParamSensitivities/re_optim_design_tornado_J1.pdf",
        "results/ParamSensitivities/nonlinear_objectives.pdf",
        "results/ParamSensitivities/intermed.mat",
        "results/ParamSensitivities/re_optim_objective_tornado.pdf",
        "results/ParamSensitivities/re_optim_objective_grid.pdf",
        "results/ParamSensitivities/post_optim_re_optim_objective_grid.pdf",
        "results/ParamSensitivities/end.mat",
        "results/ParamSensitivities/re_optim_design_tornado_J2.pdf",
        "results/ParamSensitivities/re_optim_constraint_grid.pdf",
        "results/ParamSensitivities/nonlinear_design_J1.pdf",
        "results/ParamSensitivities/post_optim_design_grid.pdf",
        "results/HydroCoeffFigFunc/end.mat",
        "results/HydroCoeffFigFunc/hydro_coeff_err.pdf",
        "results/HydroCoeffFigFunc/intermed.mat",
        "results/Constraints/end.mat",
        "results/Constraints/intermed.mat",
        "results/SparHydro/end.mat",
        "results/SparHydro/spar_added_mass.pdf",
        "results/SparHydro/intermed.mat",
        "results/Wecsim/end.mat",
        "results/Wecsim/intermed.mat",
        "results/Wecsim/WECSim_error_histograms_multibody.pdf",
        "results/Wecsim/wecsim_all_sea_states.pdf",
        "results/Wecsim/WECSim_error_histograms_singlebody.pdf",
        "results/Multistart/intermed.mat",
        "results/Multistart/end.mat",
        "results/Multistart/multistart_parallel_coordinates.pdf",
        "results/Multistart/multistart_results.tex",
        "results/Multistart/multistart_convergence_tree.pdf",
        "results/Meem/meem_matching.pdf",
        "results/Meem/meem_convergence.pdf",
        "results/Meem/meem_validation.pdf",
        "results/Meem/intermed.mat",
        "results/Meem/meem_regions.pdf",
        "results/Meem/asymptotic_b_vector.pdf",
        "results/Meem/meem_sparsity.pdf",
        "results/Meem/end.mat",
        "results/Parameters/end.mat",
        "results/Parameters/intermed.mat",
        "results/ParetoFigFunc/pareto_constraint_activity.pdf",
        "results/ParetoFigFunc/intermed.mat",
        "results/ParetoFigFunc/pareto_front_with_design_images.pdf",
        "results/ParetoFigFunc/pareto_front_LCOE_contours.pdf",
        "results/ParetoFigFunc/pareto_heuristics.pdf",
        "results/ParetoFigFunc/end.mat",
        "results/ParetoSweep/end.mat",
        "results/ParetoSweep/sweep_num_seeds.pdf",
        "results/ParetoSweep/intermed.mat",
        "results/RunSingleFigFunc/intermed.mat",
        "results/JpdMultiplyFigFunc/end.mat",
        "results/JpdMultiplyFigFunc/JPD_multiplication.pdf",
        "results/JpdMultiplyFigFunc/intermed.mat",
        "results/DesignSpaceExploration/end.mat",
        "results/DesignSpaceExploration/experiments.pdf",
        "results/DesignSpaceExploration/intermed.mat"
      ]
    },
    "uncommitted": {
      "deleted": [
        "pubs/applied-ocean-research-model/main.pdf",
        "pubs/renewable-energy-mdo/mdocean.pdf",
        "results/Comparison/intermed.mat",
        "results/GradientOptimFigFunc/intermed.mat",
        "results/RunSingleFigFunc/slamming_model_comparison.pdf",
        "results/RunSingleFigFunc/end.mat",
        "results/RunSingleFigFunc/drag_convergence.pdf",
        "results/LocationSensitivity/intermed.mat"
      ],
      "modified": [
        "results/RunSingleFigFunc/nominal_power_pdf.pdf",
        "results/RunSingleFigFunc/nominal_geometry_viz.pdf",
        "results/RunSingleFigFunc/nominal_power_matrix.pdf"
      ],
      "added": [
        "pubs/applied-ocean-research-model/out/main.pdf",
        "pubs/renewable-energy-mdo/out/mdocean.pdf"
      ]
    },
    "untracked": [],
    "unchanged": [
      "results/GradientOptimFigFunc/end.mat",
      "results/GradientOptimFigFunc/single_obj_convergence.pdf",
      "results/Comparison/probability_CDF.pdf",
      "results/LocationSensitivity/location_sensitivity.tex",
      "results/Comparison/overlaid_geometry.pdf",
      "results/GradientOptimFigFunc/dJ_dx_gradient.pdf",
      "results/GradientOptimFigFunc/lagrange_multipliers.pdf",
      "results/Wecsim/WECSim_errors.tex",
      "pubs/renewable-energy-mdo/figs/from-matlab/",
      "results/GradientOptimFigFunc/single_obj_opt_power_matrix.pdf",
      "pubs/applied-ocean-research-model/figs/manual/",
      "pubs/renewable-energy-mdo/figs/manual/",
      "results/Comparison/end.mat",
      "results/GradientOptimFigFunc/normalized_gradient.pdf",
      "results/Parameters/parameters.tex",
      "results/Comparison/optimal_design_vars.tex",
      "pubs/applied-ocean-research-model/tables/from-matlab/",
      "results/Comparison/overlaid_hydro_coeffs.pdf",
      "pubs/renewable-energy-mdo/tables/from-matlab/",
      "results/Cost/cost_parameters.tex",
      "results/Validation/validation.tex",
      "results/DesignVars/design_vars.tex",
      "pubs/applied-ocean-research-model/figs/from-matlab/",
      "results/Constraints/constraints.tex",
      "results/GradientOptimFigFunc/single_obj_opt_geometry.pdf",
      "results/LocationSensitivity/end.mat",
      "results/Comparison/optimal_outputs.tex"
    ]
  }
}